kaomojitool/README.md
kaomojitool/__init__.py
kaomojitool/__main__.py
kaomojitool/kaomoji.py
kaomoji_database_edit_tool-0.0.11.dist-info/LICENSE.txt
kaomoji_database_edit_tool-0.0.11.dist-info/METADATA
kaomoji_database_edit_tool-0.0.11.dist-info/WHEEL
kaomoji_database_edit_tool-0.0.11.dist-info/entry_points.txt
kaomoji_database_edit_tool-0.0.11.dist-info/top_level.txt
kaomoji_database_edit_tool-0.0.11.dist-info/RECORD
