Metadata-Version: 2.1
Name: kaomoji-database-edit-tool
Version: 0.0.11
Summary: Tool to edit kaomoji database .tsv
Home-page: https://github.com/iacchus/kaomoji-database-edit-tool/
Author: Iacchus Mercurius
Author-email: kassivs+git@gmail.com
License: AGPLv3
Project-URL: Documentation, https://github.com/iacchus/kaomoji-database-edit-tool/
Project-URL: Source, https://github.com/iacchus/kaomoji-database-edit-tool/
Project-URL: Tracker, https://github.com/iacchus/kaomoji-database-edit-tool/issues/
Platform: any
Classifier: Development Status :: 5 - Production/Stable
Classifier: Intended Audience :: Developers
Classifier: License :: OSI Approved :: GNU Affero General Public License v3
Classifier: Programming Language :: Python
License-File: LICENSE.txt
Requires-Dist: click
Requires-Dist: toml
Requires-Dist: importlib-metadata ; python_version < "3.8"
Provides-Extra: testing
Requires-Dist: setuptools ; extra == 'testing'
Requires-Dist: pytest ; extra == 'testing'
Requires-Dist: pytest-cov ; extra == 'testing'
